{"1":{"owner":"Ash","pokemons":[{"id":25,"name":"pikachu","weight":60,"height":4},{"id":9,"name":"blastoise","weight":855,"height":16}]},"2":{"owner":"Gabrieeel","pokemons":[{"id":4,"name":"charmander","weight":85,"height":6},{"id":9,"name":"blastoise","weight":855,"height":16}]},"3":{"owner":"ddc01f9bb7f463ad3f08f49615b3a490b65a6597","team":[{"id":25,"name":"pikachu","weight":60,"height":4}]},"4":{"owner":"09a14c2d573aac88f6ea433f08f81bd1f6ad4c30","team":[{"id":25,"name":"pikachu","weight":60,"height":4}]},"5":{"owner":"bbe04fc7d32ffe871b823c0d287e583942351a95","team":[{"id":25,"name":"pikachu","weight":60,"height":4}]}}